vsaiortc/__init__.py
vsaiortc/clock.py
vsaiortc/events.py
vsaiortc/exceptions.py
vsaiortc/jitterbuffer.py
vsaiortc/mediastreams.py
vsaiortc/py.typed
vsaiortc/rate.py
vsaiortc/rtcconfiguration.py
vsaiortc/rtcdatachannel.py
vsaiortc/rtcdtlstransport.py
vsaiortc/rtcicetransport.py
vsaiortc/rtcpeerconnection.py
vsaiortc/rtcrtpparameters.py
vsaiortc/rtcrtpreceiver.py
vsaiortc/rtcrtpsender.py
vsaiortc/rtcrtptransceiver.py
vsaiortc/rtcsctptransport.py
vsaiortc/rtcsessiondescription.py
vsaiortc/rtp.py
vsaiortc/sdp.py
vsaiortc/stats.py
vsaiortc/utils.py
vsaiortc/codecs/__init__.py
vsaiortc/codecs/base.py
vsaiortc/codecs/g711.py
vsaiortc/codecs/g722.py
vsaiortc/codecs/h264.py
vsaiortc/codecs/opus.py
vsaiortc/codecs/vpx.py
vsaiortc/contrib/__init__.py
vsaiortc/contrib/media.py
vsaiortc/contrib/signaling.py
vsaiortc-0.0.9.dist-info/licenses/LICENSE
vsaiortc-0.0.9.dist-info/METADATA
vsaiortc-0.0.9.dist-info/WHEEL
vsaiortc-0.0.9.dist-info/top_level.txt
vsaiortc-0.0.9.dist-info/RECORD
