Metadata-Version: 2.4
Name: vsaiortc
Version: 0.0.9
Summary: An implementation of WebRTC and ORTC
Author-email: Yash Chudasama <yash@videosdk.live>, Ankit Chotaliya <ankit@videosdk.live>
License-Expression: BSD-3-Clause
Project-URL: homepage, https://github.com/zujonow/vs-aiortc
Project-URL: issues, https://github.com/zujonow/vs-aiortc/issues
Project-URL: documentation, https://docs.videosdk.live
Classifier: Development Status :: 4 - Beta
Classifier: Environment :: Web Environment
Classifier: Intended Audience :: Developers
Classifier: Operating System :: OS Independent
Classifier: Programming Language :: Python
Classifier: Programming Language :: Python :: 3
Classifier: Programming Language :: Python :: 3.9
Classifier: Programming Language :: Python :: 3.10
Classifier: Programming Language :: Python :: 3.11
Classifier: Programming Language :: Python :: 3.12
Classifier: Programming Language :: Python :: 3.13
Requires-Python: >=3.9
License-File: LICENSE
Requires-Dist: aioice<1.0.0,>=0.10.1
Requires-Dist: av<15.0.0,>=14.0.0
Requires-Dist: cryptography>=44.0.0
Requires-Dist: google-crc32c>=1.1
Requires-Dist: pyee>=13.0.0
Requires-Dist: pylibsrtp>=0.10.0
Requires-Dist: pyopenssl>=25.0.0
Provides-Extra: dev
Requires-Dist: aiohttp>=3.7.0; extra == "dev"
Requires-Dist: coverage[toml]>=7.2.2; extra == "dev"
Requires-Dist: numpy>=1.19.0; extra == "dev"
Dynamic: license-file
